pretix_cwa/__init__.py
pretix_cwa/apps.py
pretix_cwa/forms.py
pretix_cwa/generator.py
pretix_cwa/signals.py
pretix_cwa/tasks.py
pretix_cwa/urls.py
pretix_cwa/views.py
pretix_cwa/locale/django.pot
pretix_cwa/locale/de/LC_MESSAGES/django.mo
pretix_cwa/locale/de/LC_MESSAGES/django.po
pretix_cwa/locale/de_Informal/.gitkeep
pretix_cwa/locale/de_Informal/LC_MESSAGES/django.mo
pretix_cwa/locale/de_Informal/LC_MESSAGES/django.po
pretix_cwa/static/pretix_cwa/.gitkeep
pretix_cwa/static/pretix_cwa/logo.svg
pretix_cwa/static/pretix_cwa/signage.scss
pretix_cwa/templates/pretix_cwa/.gitkeep
pretix_cwa/templates/pretix_cwa/settings.html
pretix_cwa/templates/pretix_cwa/signage.html
pretix_cwa-1.1.2.dist-info/LICENSE
pretix_cwa-1.1.2.dist-info/METADATA
pretix_cwa-1.1.2.dist-info/WHEEL
pretix_cwa-1.1.2.dist-info/entry_points.txt
pretix_cwa-1.1.2.dist-info/top_level.txt
pretix_cwa-1.1.2.dist-info/RECORD
