Metadata-Version: 2.1
Name: pretix-cwa
Version: 1.1.2
Summary: pretix integration for the Corona Warn App (CWA)
Author-email: pretix team <support@pretix.eu>
Maintainer-email: pretix team <support@pretix.eu>
License: 
Project-URL: homepage, https://github.com/pretix/pretix-cwa
Keywords: pretix
Requires-Python: >=3.9
License-File: LICENSE
Requires-Dist: qrcode
Requires-Dist: cwa-qr (>=1.2.2)
